projectrestore/__init__.py
projectrestore/banner.py
projectrestore/cli.py
projectrestore/restore_engine.py
projectrestore/modules/__init__.py
projectrestore/modules/checksum.py
projectrestore/modules/extraction.py
projectrestore/modules/locking.py
projectrestore/modules/signals.py
projectrestore/modules/utils.py
projectrestore-4.0.1.dist-info/METADATA
projectrestore-4.0.1.dist-info/WHEEL
projectrestore-4.0.1.dist-info/entry_points.txt
projectrestore-4.0.1.dist-info/top_level.txt
projectrestore-4.0.1.dist-info/RECORD
