Metadata-Version: 2.4
Name: projectrestore
Version: 4.0.1
Summary: Safely extract and restore project snapshots created by projectclone — secure, atomic, integrity-checked restore engine.
Author-email: Dhruv <dhruv13x@gmail.com>
Maintainer-email: Dhruv <dhruv13x@gmail.com>
License: MIT
Project-URL: Homepage, https://github.com/dhruv13x/projectrestore
Project-URL: Repository, https://github.com/dhruv13x/projectrestore.git
Project-URL: Issues, https://github.com/dhruv13x/projectrestore/issues
Keywords: restore,backup-restore,snapshot,archive-extract,projectclone,reproducibility,developer-tools,atomic-restore,safe-restore
Classifier: Development Status :: 4 - Beta
Classifier: Environment :: Console
Classifier: Intended Audience :: Developers
Classifier: Topic :: System :: Archiving
Classifier: Topic :: System :: Recovery Tools
Classifier: Topic :: Utilities
Classifier: License :: OSI Approved :: MIT License
Classifier: Operating System :: OS Independent
Classifier: Programming Language :: Python :: 3
Classifier: Programming Language :: Python :: 3 :: Only
Requires-Python: >=3.8
Provides-Extra: dev
Requires-Dist: pytest>=8.0; extra == "dev"
Requires-Dist: pytest-cov>=5.0; extra == "dev"
Requires-Dist: black>=24.0; extra == "dev"
Requires-Dist: mypy>=1.10; extra == "dev"
Requires-Dist: ruff>=0.4.0; extra == "dev"
